dsdLab/Lab10-FlipFlopsAndRegisters/Q5-6BitShiftReg/sixBitShiftReg.v
module sixBitShiftReg(inp,clk,o);
    input inp;
    input clk;
    output o;

    wire [4:0] t;

    dFF ff1(inp,clk,t[4]);
    dFF ff2(t[4],clk,t[3]);
    dFF ff3(t[3],clk,t[2]);
    dFF ff4(t[2],clk,t[1]);
    dFF ff5(t[1],clk,t[0]);
    dFF ff6(t[0],clk,o);

endmodule

module dFF(d,clk,q);
    input d,clk;
    output reg q;

    always @(posedge clk)
        q <= d;

endmodule

dsdLab/Lab10-FlipFlopsAndRegisters/Q5-6BitShiftReg/sixBitShiftReg_tb.v
`timescale 1ns/1ns
`include "sixBitShiftReg.v"

module sixBitShiftReg_tb();
reg inp;
reg clk;
wire o;

sixBitShiftReg fbr(inp,clk,o);
always #10 clk = ~clk;
initial
begin
    $dumpfile("sixBitShiftReg_tb.vcd");
    $dumpvars(0,sixBitShiftReg_tb);
    clk = 0;
    #280 $finish;
end
initial
begin
    inp = 1; #15;
    inp = 0; #20;
    inp = 1; #20;
    inp = 1; #20;
    inp = 0; #20;
    inp = 0; #20;

end
endmodule

dsdLab/Lab10-FlipFlopsAndRegisters/Q5-6BitShiftReg/sixBitShiftReg_tb.vcd
$date
	Mon Jan 23 09:59:22 2023
$end
$version
	Icarus Verilog
$end
$timescale
	1ns
$end
$scope module sixBitShiftReg_tb $end
$var wire 1 ! o $end
$var reg 1 " clk $end
$var reg 1 # inp $end
$scope module fbr $end
$var wire 1 " clk $end
$var wire 1 # inp $end
$var wire 5 $ t [4:0] $end
$var wire 1 ! o $end
$scope module ff1 $end
$var wire 1 " clk $end
$var wire 1 # d $end
$var reg 1 % q $end
$upscope $end
$scope module ff2 $end
$var wire 1 " clk $end
$var wire 1 & d $end
$var reg 1 ' q $end
$upscope $end
$scope module ff3 $end
$var wire 1 " clk $end
$var wire 1 ( d $end
$var reg 1 ) q $end
$upscope $end
$scope module ff4 $end
$var wire 1 " clk $end
$var wire 1 * d $end
$var reg 1 + q $end
$upscope $end
$scope module ff5 $end
$var wire 1 " clk $end
$var wire 1 , d $end
$var reg 1 - q $end
$upscope $end
$scope module ff6 $end
$var wire 1 " clk $end
$var wire 1 . d $end
$var reg 1 ! q $end
$upscope $end
$upscope $end
$upscope $end
$enddefinitions $end
#0
$dumpvars
x.
x-
x,
x+
x*
x)
x(
x'
x&
x%
bx $
1#
0"
x!
$end
#10
1&
b1xxxx $
1%
1"
#15
0#
#20
0"
#30
1(
0&
1'
b1xxx $
0%
1"
#35
1#
#40
0"
#50
1&
0(
1*
1%
0'
b101xx $
1)
1"
#60
0"
#70
1,
0*
1(
1+
0)
b1101x $
1'
1"
#75
0#
#80
0"
#90
0&
1*
0,
1.
0%
1)
0+
b1101 $
1-
1"
#100
0"
#110
0.
1,
0(
1!
0-
1+
b110 $
0'
1"
#120
0"
#130
0*
1.
0)
b11 $
1-
0!
1"
#140
0"
#150
0,
1!
b1 $
0+
1"
#160
0"
#170
0.
b0 $
0-
1"
#180
0"
#190
0!
1"
