dsdLab/Lab9-ApplicationsOfDecoders/Q3-3InputMajority/threeInpMajority.v
/* This is using one decoder
module threeInpMajority(w,f);
    input [2:0] w;
    output f;

    wire [0:3] y;

    TwoToFourDecoder stage0(w[2:1],1'b1,y);
    and(t1,w[0],y[1]);
    and(t2,y[1],y[2]);
    and(t3,w[0],y[2]);
    or(f,t1,t2,t3,y[3]);

endmodule */

//Using 2 decoders: 

module threeInpMajority(w,f);
    input [2:0] w;
    output f;

    wire [0:3] y1;
    wire [0:3] y2;

    TwoToFourDecoder stage0(w[1:0],1'b1,y1);
    TwoToFourDecoder stage1(w[2:1],1'b1,y2);
    and(t1,y1[1],y1[2]);
    and(t2,y1[1],y2[2]);
    and(t3,y2[1],y2[2]);
    or(f,t1,t2,t3,y1[3],y2[3]);

endmodule

module TwoToFourDecoder(w,En,y);
    input [1:0] w;
    input En;
    output reg [0:3] y;
    integer k;

    always @(w or En)
    for (k = 0; k <= 3; k=k+1)
        if ((w==k) && (En == 1))
            y[k] = 1;
        else
            y[k] = 0;
endmodule

dsdLab/Lab9-ApplicationsOfDecoders/Q3-3InputMajority/threeInpMajority_tb.v
`timescale 1ns/1ns
`include "threeInpMajority.v"

module threeInpMajority_tb();
reg [2:0] w;
wire f;

threeInpMajority q(w,f);
initial
begin 

    $dumpfile("threeInpMajority_tb.vcd");
    $dumpvars(0,threeInpMajority_tb);

    w = 3'b000; #20;
    w = 3'b001; #20;
    w = 3'b010; #20;
    w = 3'b011; #20;
    w = 3'b100; #20;
    w = 3'b101; #20;
    w = 3'b110; #20;
    w = 3'b111; #20;

    $display("Test Complete");

end
endmodule

dsdLab/Lab9-ApplicationsOfDecoders/Q3-3InputMajority/threeInpMajority_tb.vcd
$date
	Mon Oct 31 15:24:39 2022
$end
$version
	Icarus Verilog
$end
$timescale
	1ns
$end
$scope module threeInpMajority_tb $end
$var wire 1 ! f $end
$var reg 3 " w [2:0] $end
$scope module q $end
$var wire 1 ! f $end
$var wire 1 # t1 $end
$var wire 1 $ t2 $end
$var wire 1 % t3 $end
$var wire 3 & w [2:0] $end
$var wire 4 ' y2 [0:3] $end
$var wire 4 ( y1 [0:3] $end
$scope module stage0 $end
$var wire 1 ) En $end
$var wire 2 * w [1:0] $end
$var reg 4 + y [0:3] $end
$var integer 32 , k [31:0] $end
$upscope $end
$scope module stage1 $end
$var wire 1 - En $end
$var wire 2 . w [1:0] $end
$var reg 4 / y [0:3] $end
$var integer 32 0 k [31:0] $end
$upscope $end
$upscope $end
$upscope $end
$enddefinitions $end
#0
$dumpvars
b100 0
b1000 /
b0 .
1-
b100 ,
b1000 +
b0 *
1)
b1000 (
b1000 '
b0 &
0%
0$
0#
b0 "
0!
$end
#20
b100 (
b100 +
b100 ,
b1 *
b1 "
b1 &
#40
b10 (
b10 +
b100 ,
b100 '
b100 /
b100 0
b10 *
b1 .
b10 "
b10 &
#60
1!
b1 (
b1 +
b100 ,
b11 *
b11 "
b11 &
#80
0!
b1000 (
b1000 +
b100 ,
b10 '
b10 /
b100 0
b0 *
b10 .
b100 "
b100 &
#100
1!
1$
b100 (
b100 +
b100 ,
b1 *
b101 "
b101 &
#120
0$
b10 (
b10 +
b100 ,
b1 '
b1 /
b100 0
b10 *
b11 .
b110 "
b110 &
#140
b1 (
b1 +
b100 ,
b11 *
b111 "
b111 &
