dsdLab/Lab11-Counters/Q5-SynchronousUpDownCounter/upDownCounter.v
module upDownCounter(up,down,clk,reset,Q);
    input up,down,clk,reset;
    output [3:0] Q;
    wire t0,t1,t2,t3,t4;
    jkFF ff1(1'b1,1'b1,clk,reset,Q[0]);
    assign t0 = (up & Q[0]) | (~up & ~Q[0]);
    jkFF ff2(t0,t0,clk,reset,Q[1]);
    assign t1 = (up & Q[1] & Q[0]) | (~up & ~Q[1] & ~Q[0]);
    jkFF ff3(t1,t1,clk,reset,Q[2]);
    assign t2 = (up & Q[2] & Q[1] & Q[0]) | (~up & Q[2] & ~Q[1] & ~Q[0]);
    jkFF ff4(t2,t2,clk,reset,Q[3]);

endmodule

module jkFF(j,k,clk,reset,q);
    input j,k,clk,reset;
    output reg q;

    always @(posedge clk)
    begin
        if (reset)
            q <= 0;
        else
        begin
            if (clk)
            begin
                if (!q)
                begin
                    if (j)
                        q <= 1;
                end
                else
                begin
                    if (k) 
                        q <= 0;
                end
            end
        end
    end

    always @(reset)
    begin 
        if (reset)
            q <= 0;
    end
endmodule

dsdLab/Lab11-Counters/Q5-SynchronousUpDownCounter/upDownCounter_tb.v
`timescale 1ns/1ns
`include "upDownCounter.v"

module upDownCounter_tb();
reg up,down,clk,reset;
wire [0:3] Q;

upDownCounter upDownCounterq(up,down,clk,reset,Q);
always #10 clk = ~clk;
initial
begin
    $dumpfile("upDownCounter_tb.vcd");
    $dumpvars(0,upDownCounter_tb);
    clk = 0;
    #100 $finish;
end
initial
begin
    up = 0; down = 0; reset = 1; #20;
    up = 1; down = 0; reset = 0; #20;
    up = 1; down = 0; reset = 0; #20;
    up = 0; down = 1; reset = 0; #20;
    up = 1; down = 0; reset = 0; #20;

    $display("Test complete");
end
endmodule

dsdLab/Lab11-Counters/Q5-SynchronousUpDownCounter/upDownCounter_tb.vcd
$date
	Mon Nov 21 16:25:54 2022
$end
$version
	Icarus Verilog
$end
$timescale
	1ns
$end
$scope module upDownCounter_tb $end
$var wire 4 ! Q [0:3] $end
$var reg 1 " clk $end
$var reg 1 # down $end
$var reg 1 $ reset $end
$var reg 1 % up $end
$scope module upDownCounterq $end
$var wire 1 " clk $end
$var wire 1 # down $end
$var wire 1 $ reset $end
$var wire 1 & t0 $end
$var wire 1 ' t1 $end
$var wire 1 ( t2 $end
$var wire 1 % up $end
$var wire 4 ) Q [3:0] $end
$scope module ff1 $end
$var wire 1 " clk $end
$var wire 1 * j $end
$var wire 1 + k $end
$var wire 1 $ reset $end
$var reg 1 , q $end
$upscope $end
$scope module ff2 $end
$var wire 1 " clk $end
$var wire 1 & j $end
$var wire 1 & k $end
$var wire 1 $ reset $end
$var reg 1 - q $end
$upscope $end
$scope module ff3 $end
$var wire 1 " clk $end
$var wire 1 ' j $end
$var wire 1 ' k $end
$var wire 1 $ reset $end
$var reg 1 . q $end
$upscope $end
$scope module ff4 $end
$var wire 1 " clk $end
$var wire 1 ( j $end
$var wire 1 ( k $end
$var wire 1 $ reset $end
$var reg 1 / q $end
$upscope $end
$upscope $end
$upscope $end
$enddefinitions $end
#0
$dumpvars
0/
0.
0-
0,
1+
1*
b0 )
0(
1'
1&
0%
1$
0#
0"
b0 !
$end
#10
1"
#20
0'
0&
0"
0$
1%
#30
1&
b1 !
b1 )
1,
1"
#40
0"
#50
0&
0,
b10 !
b10 )
1-
1"
#60
1&
0"
1#
0%
#70
0&
0-
b1 !
b1 )
1,
1"
#80
1&
0"
0#
1%
#90
0&
0,
b10 !
b10 )
1-
1"
