dsdLab/Lab7-MultiplexerApplications/Q1-ImplementingFunctions/q1B/q1b.v
module q1b(a,b,c,d,f);
    input a,b,c,d;
    output f;

    wire [1:0] h;
    assign h = {a,b};

    MUX4to1 stage0(h,c,d,f);

endmodule

module MUX4to1(s,c,d,f);
    input [1:0] s;
    input c,d;
    output f;
    reg f;
    wire t1;
    assign t1 = ~d | c;

    always @(s)

    case (s)
        0: f = t1;
        1: f = d;
        2: f = 0;
        3: f = 0;
    endcase

endmodule

dsdLab/Lab7-MultiplexerApplications/Q1-ImplementingFunctions/q1B/q1b_tb.v
`timescale 1ns/1ns
`include "q1b.v"

module q1b_tb();
reg a,b,c,d;
wire f;

q1b q(a,b,c,d,f);
initial 
begin 

    $dumpfile("q1b_tb.vcd");
    $dumpvars(0,q1b_tb);

    a=0; b=0; c=0; d=0;#20;
	a=0; b=0; c=0; d=1;#20;
	a=0; b=0; c=1; d=0;#20;
	a=0; b=0; c=1; d=1;#20;
	a=0; b=1; c=0; d=0;#20;
	a=0; b=1; c=0; d=1;#20;
	a=0; b=1; c=1; d=0;#20;
	a=0; b=1; c=1; d=1;#20;
	a=1; b=0; c=0; d=0;#20;
	a=1; b=0; c=0; d=1;#20;
	a=1; b=0; c=1; d=0;#20;
	a=1; b=0; c=1; d=1;#20;
	a=1; b=1; c=0; d=0;#20;
	a=1; b=1; c=0; d=1;#20;
	a=1; b=1; c=1; d=0;#20;
	a=1; b=1; c=1; d=1;#20;

    $display("Test Complete");

end
endmodule

dsdLab/Lab7-MultiplexerApplications/Q1-ImplementingFunctions/q1B/q1b_tb.vcd
$date
	Mon Oct 10 16:20:54 2022
$end
$version
	Icarus Verilog
$end
$timescale
	1ns
$end
$scope module q1b_tb $end
$var wire 1 ! f $end
$var reg 1 " a $end
$var reg 1 # b $end
$var reg 1 $ c $end
$var reg 1 % d $end
$scope module q $end
$var wire 1 " a $end
$var wire 1 # b $end
$var wire 1 $ c $end
$var wire 1 % d $end
$var wire 2 & h [1:0] $end
$var wire 1 ! f $end
$scope module stage0 $end
$var wire 1 $ c $end
$var wire 1 % d $end
$var wire 2 ' s [1:0] $end
$var wire 1 ( t1 $end
$var reg 1 ! f $end
$upscope $end
$upscope $end
$upscope $end
$enddefinitions $end
#0
$dumpvars
1(
b0 '
b0 &
0%
0$
0#
0"
x!
$end
#20
0(
1%
#40
1(
0%
1$
#60
1%
#80
1(
0!
0%
0$
b1 &
b1 '
1#
#100
0(
1%
#120
1(
0%
1$
#140
1%
#160
1(
0%
0$
0#
b10 &
b10 '
1"
#180
0(
1%
#200
1(
0%
1$
#220
1%
#240
1(
0%
0$
b11 &
b11 '
1#
#260
0(
1%
#280
1(
0%
1$
#300
1%
