dsdLab/Lab7-MultiplexerApplications/Q1-ImplementingFunctions/q1B/q1b.v
module q1b(a,b,c,d,f);
    input a,b,c,d;
    output f;
    wire [3:0] t;
    wire [1:0] h;
    assign h = {a,b};
    assign t = {1'b0, 1'b0, d, ~d | c};
    MUX4to1 stage0(t,h,f);

endmodule

module MUX4to1(w,s,f);
    input [3:0] w;
    input [1:0] s;
    output f;
    reg f;

    always @(w or s)
    f = s[0] ? ( s[1] ? w[3] : w[1] ) : ( s[1] ? w[2] : w[0]);

endmodule

dsdLab/Lab7-MultiplexerApplications/Q1-ImplementingFunctions/q1B/q1b_tb.v
`timescale 1ns/1ns
`include "q1b.v"

module q1b_tb();
reg a,b,c,d;
wire f;

q1b q(a,b,c,d,f);
initial 
begin 

    $dumpfile("q1b_tb.vcd");
    $dumpvars(0,q1b_tb);

    a=0; b=0; c=0; d=0;#20;
	a=0; b=0; c=0; d=1;#20;
	a=0; b=0; c=1; d=0;#20;
	a=0; b=0; c=1; d=1;#20;
	a=0; b=1; c=0; d=0;#20;
	a=0; b=1; c=0; d=1;#20;
	a=0; b=1; c=1; d=0;#20;
	a=0; b=1; c=1; d=1;#20;
	a=1; b=0; c=0; d=0;#20;
	a=1; b=0; c=0; d=1;#20;
	a=1; b=0; c=1; d=0;#20;
	a=1; b=0; c=1; d=1;#20;
	a=1; b=1; c=0; d=0;#20;
	a=1; b=1; c=0; d=1;#20;
	a=1; b=1; c=1; d=0;#20;
	a=1; b=1; c=1; d=1;#20;

    $display("Test Complete");

end
endmodule

dsdLab/Lab7-MultiplexerApplications/Q1-ImplementingFunctions/q1B/q1b_tb.vcd
$date
	Sun Jan 22 14:19:03 2023
$end
$version
	Icarus Verilog
$end
$timescale
	1ns
$end
$scope module q1b_tb $end
$var wire 1 ! f $end
$var reg 1 " a $end
$var reg 1 # b $end
$var reg 1 $ c $end
$var reg 1 % d $end
$scope module q $end
$var wire 1 " a $end
$var wire 1 # b $end
$var wire 1 $ c $end
$var wire 1 % d $end
$var wire 4 & t [3:0] $end
$var wire 2 ' h [1:0] $end
$var wire 1 ! f $end
$scope module stage0 $end
$var wire 2 ( s [1:0] $end
$var wire 4 ) w [3:0] $end
$var reg 1 ! f $end
$upscope $end
$upscope $end
$upscope $end
$enddefinitions $end
#0
$dumpvars
b1 )
b0 (
b0 '
b1 &
0%
0$
0#
0"
1!
$end
#20
0!
b10 &
b10 )
1%
#40
1!
b1 &
b1 )
0%
1$
#60
b11 &
b11 )
1%
#80
0!
b1 &
b1 )
0%
0$
b1 '
b1 (
1#
#100
1!
b10 &
b10 )
1%
#120
0!
b1 &
b1 )
0%
1$
#140
1!
b11 &
b11 )
1%
#160
0!
b1 &
b1 )
0%
0$
0#
b10 '
b10 (
1"
#180
b10 &
b10 )
1%
#200
b1 &
b1 )
0%
1$
#220
b11 &
b11 )
1%
#240
b1 &
b1 )
0%
0$
b11 '
b11 (
1#
#260
b10 &
b10 )
1%
#280
b1 &
b1 )
0%
1$
#300
b11 &
b11 )
1%
