dsdlLab/Lab2/Exercise1/Part2/exercise2.v
module exercise2(a,b,c,d,f);
	input a,b,c,d;
	output f;
	
	assign f = ((b & ~c & ~d) | (~b & d) | (c & ~b));
	
endmodule

dsdLab/Lab2-KMaps/Exercise1/Part2/exercise2_tb.v
`timescale 1ns/1ns
`include "exercise2.v" 

module exercise2_tb();
reg a,b,c,d;
wire f;

exercise2 ex2(a,b,c,d,f);
initial 
begin

	$dumpfile("exercise2_tb.vcd");
	$dumpvars(0,exercise2_tb);
	
	a=1'b0; b=1'b0; c=1'b0; d=1'b0;
	#20;
	
	a=1'b0; b=1'b0; c=1'b0; d=1'b1;
	#20;
	
	a=1'b0; b=1'b0; c=1'b1; d=1'b0;
	#20;
	
	a=1'b0; b=1'b0; c=1'b1; d=1'b1;
	#20;
	
	a=1'b0; b=1'b1; c=1'b0; d=1'b0;
	#20;
	
	a=1'b0; b=1'b1; c=1'b0; d=1'b1;
	#20;
	
	a=1'b0; b=1'b1; c=1'b1; d=1'b0;
	#20;
	
	a=1'b0; b=1'b1; c=1'b1; d=1'b1;
	#20;
	
	a=1'b1; b=1'b0; c=1'b0; d=1'b0;
	#20;
	
	a=1'b1; b=1'b0; c=1'b0; d=1'b1;
	#20;
	
	a=1'b1; b=1'b0; c=1'b1; d=1'b0;
	#20;
	
	a=1'b1; b=1'b0; c=1'b1; d=1'b1;
	#20;
	
	a=1'b1; b=1'b1; c=1'b0; d=1'b0;
	#20;
	
	a=1'b1; b=1'b1; c=1'b0; d=1'b1;
	#20;
	
	a=1'b1; b=1'b1; c=1'b1; d=1'b0;
	#20;
	
	a=1'b1; b=1'b1; c=1'b1; d=1'b1;
	#20;
	$display("Test Complete");
end

endmodule

dsdLab/Lab2/Exercise1/Part2/exercise2_tb.vcd
$date
	Sun Sep  4 11:23:46 2022
$end
$version
	Icarus Verilog
$end
$timescale
	1ns
$end
$scope module exercise2_tb $end
$var wire 1 ! f $end
$var reg 1 " a $end
$var reg 1 # b $end
$var reg 1 $ c $end
$var reg 1 % d $end
$scope module ex2 $end
$var wire 1 " a $end
$var wire 1 # b $end
$var wire 1 $ c $end
$var wire 1 % d $end
$var wire 1 ! f $end
$upscope $end
$upscope $end
$enddefinitions $end
#0
$dumpvars
0%
0$
0#
0"
0!
$end
#20
1!
1%
#40
0%
1$
#60
1%
#80
1!
0%
0$
1#
#100
0!
1%
#120
0%
1$
#140
1%
#160
0%
0$
0#
1"
#180
1!
1%
#200
0%
1$
#220
1%
#240
1!
0%
0$
1#
#260
0!
1%
#280
0%
1$
#300
1%
