dsdLab/Lab7-MultiplexerApplications/Q2-3InputMajorityFunction/Part1/q1a.v
module q1a(w,f);
    input [2:0] w;
    output f;

    MUX2to1 stage0(w[1:0],w[2],f);

endmodule

module MUX2to1(w,s,f);
    input [1:0] w;
    input s;
    output f;
    reg f;
    wire t1,t2;
    assign t1 = w[0] & w[1];
    assign t2 = w[0] & ~w[1];

    always @(w or s)
    begin 
        f = t2;
        if(s == 0)
            f = t1;
    end
endmodule

dsdLab/Lab7-MultiplexerApplications/Q2-3InputMajorityFunction/Part1/q1a_tb.v
`timescale 1ns/1ns
`include "q1a.v"

module q1a_tb();
reg [2:0] w;
wire f;

q1a q(w,f);
initial
begin 

    $dumpfile("q1a_tb.vcd");
    $dumpvars(0,q1a_tb);

    w = 3'b000; #20;
    w = 3'b001; #20;
    w = 3'b010; #20;
    w = 3'b011; #20;
    w = 3'b100; #20;
    w = 3'b101; #20;
    w = 3'b110; #20;
    w = 3'b111; #20;

    $display("Test Complete");

end
endmodule

dsdLab/Lab7-MultiplexerApplications/Q2-3InputMajorityFunction/Part1/q1a_tb.vcd
$date
	Mon Oct 10 16:46:12 2022
$end
$version
	Icarus Verilog
$end
$timescale
	1ns
$end
$scope module q1a_tb $end
$var wire 1 ! f $end
$var reg 3 " w [2:0] $end
$scope module q $end
$var wire 3 # w [2:0] $end
$var wire 1 ! f $end
$scope module stage0 $end
$var wire 1 $ s $end
$var wire 1 % t1 $end
$var wire 1 & t2 $end
$var wire 2 ' w [1:0] $end
$var reg 1 ! f $end
$upscope $end
$upscope $end
$upscope $end
$enddefinitions $end
#0
$dumpvars
b0 '
0&
0%
0$
b0 #
b0 "
x!
$end
#20
1&
0!
b1 '
b1 "
b1 #
#40
0&
0!
b10 '
b10 "
b10 #
#60
1%
b11 '
b11 "
b11 #
#80
0%
b0 '
1$
b100 "
b100 #
#100
1&
b1 '
b101 "
b101 #
#120
0&
1!
b10 '
b110 "
b110 #
#140
1%
0!
b11 '
b111 "
b111 #
