dsdLab/Lab11-Counters/Q2-5BitJohnsonCounter/johnsonCounter.v
module johnsonCounter(clk,reset,Q);
    input clk,reset;
    output [4:0] Q;
    dFF ff1(~Q[0],clk,reset,Q[4]);
    dFF ff2(Q[4],clk,reset,Q[3]);
    dFF ff3(Q[3],clk,reset,Q[2]);
    dFF ff4(Q[2],clk,reset,Q[1]);
    dFF ff5(Q[1],clk,reset,Q[0]);

endmodule

module dFF(d,clk,reset,q);
    input d,clk,reset;
    output reg q;

    always @(posedge clk)
        if (!reset)
            q <= d;

    always @(reset)
        if (reset)
            q <= 0;

endmodule

dsdLab/Lab11-Counters/Q2-5BitJohnsonCounter/johnsonCounter_tb.v
`timescale 1ns/1ns
`include "johnsonCounter.v"

module johnsonCounter_tb();
reg clk,reset;
wire [4:0] Q;

johnsonCounter johnsonCounterq(clk,reset,Q);
always #10 clk = ~clk;
initial
begin
    $dumpfile("johnsonCounter_tb.vcd");
    $dumpvars(0,johnsonCounter_tb);
    clk = 0;
    #220 $finish;
end
initial
begin
    reset = 1; #20;
    reset = 0; #200;
    $display("Test complete");
end
endmodule

dsdLab/Lab11-Counters/Q2-5BitJohnsonCounter/johnsonCounter_tb.vcd
$date
	Mon Nov 21 15:13:20 2022
$end
$version
	Icarus Verilog
$end
$timescale
	1ns
$end
$scope module johnsonCounter_tb $end
$var wire 5 ! Q [4:0] $end
$var reg 1 " clk $end
$var reg 1 # reset $end
$scope module johnsonCounterq $end
$var wire 1 " clk $end
$var wire 1 # reset $end
$var wire 5 $ Q [4:0] $end
$scope module ff1 $end
$var wire 1 " clk $end
$var wire 1 % d $end
$var wire 1 # reset $end
$var reg 1 & q $end
$upscope $end
$scope module ff2 $end
$var wire 1 " clk $end
$var wire 1 ' d $end
$var wire 1 # reset $end
$var reg 1 ( q $end
$upscope $end
$scope module ff3 $end
$var wire 1 " clk $end
$var wire 1 ) d $end
$var wire 1 # reset $end
$var reg 1 * q $end
$upscope $end
$scope module ff4 $end
$var wire 1 " clk $end
$var wire 1 + d $end
$var wire 1 # reset $end
$var reg 1 , q $end
$upscope $end
$scope module ff5 $end
$var wire 1 " clk $end
$var wire 1 - d $end
$var wire 1 # reset $end
$var reg 1 . q $end
$upscope $end
$upscope $end
$upscope $end
$enddefinitions $end
#0
$dumpvars
0.
0-
0,
0+
0*
0)
0(
0'
0&
1%
b0 $
1#
0"
b0 !
$end
#10
1"
#20
0"
0#
#30
1'
b10000 !
b10000 $
1&
1"
#40
0"
#50
1)
b11000 !
b11000 $
1(
1"
#60
0"
#70
1+
b11100 !
b11100 $
1*
1"
#80
0"
#90
1-
b11110 !
b11110 $
1,
1"
#100
0"
#110
0%
b11111 !
b11111 $
1.
1"
#120
0"
#130
0'
b1111 !
b1111 $
0&
1"
#140
0"
#150
0)
b111 !
b111 $
0(
1"
#160
0"
#170
0+
b11 !
b11 $
0*
1"
#180
0"
#190
0-
b1 !
b1 $
0,
1"
#200
0"
#210
1%
b0 !
b0 $
0.
1"
