dsdLab/Lab2/Exercise3/exercise1.v
module exercise1(x1,x2,x3,x4,f);
	input x1,x2,x3,x4;
	output f;
	
	assign f = ((x4 & x1 & x2) | (x3 & x1 & x2) | (x1 & x3 & x4) | (x2 & x3 & x4));
	
endmodule

dsdLab/Lab2-KMaps/Exercise3/exercise1_tb.v
`timescale 1ns/1ns
`include "exercise1.v" 

module exercise1_tb();
reg x1,x2,x3,x4;
wire f;

exercise1 ex1(x1,x2,x3,x4,f);
initial 
begin

	$dumpfile("exercise1_tb.vcd");
	$dumpvars(0,exercise1_tb);
	
	x1=1'b0; x2=1'b0; x3=1'b0; x4=1'b0;
	#20;
	
	x1=1'b0; x2=1'b0; x3=1'b0; x4=1'b1;
	#20;
	
	x1=1'b0; x2=1'b0; x3=1'b1; x4=1'b0;
	#20;
	
	x1=1'b0; x2=1'b0; x3=1'b1; x4=1'b1;
	#20;
	
	x1=1'b0; x2=1'b1; x3=1'b0; x4=1'b0;
	#20;
	
	x1=1'b0; x2=1'b1; x3=1'b0; x4=1'b1;
	#20;
	
	x1=1'b0; x2=1'b1; x3=1'b1; x4=1'b0;
	#20;
	
	x1=1'b0; x2=1'b1; x3=1'b1; x4=1'b1;
	#20;
	
	x1=1'b1; x2=1'b0; x3=1'b0; x4=1'b0;
	#20;
	
	x1=1'b1; x2=1'b0; x3=1'b0; x4=1'b1;
	#20;
	
	x1=1'b1; x2=1'b0; x3=1'b1; x4=1'b0;
	#20;
	
	x1=1'b1; x2=1'b0; x3=1'b1; x4=1'b1;
	#20;
	
	x1=1'b1; x2=1'b1; x3=1'b0; x4=1'b0;
	#20;
	
	x1=1'b1; x2=1'b1; x3=1'b0; x4=1'b1;
	#20;
	
	x1=1'b1; x2=1'b1; x3=1'b1; x4=1'b0;
	#20;
	
	x1=1'b1; x2=1'b1; x3=1'b1; x4=1'b1;
	#20;
	$display("Test Complete");
end

endmodule

dsdLab/Lab2/Exercise3/exercise1_tb.vcd
$date
	Mon Aug 29 14:51:57 2022
$end
$version
	Icarus Verilog
$end
$timescale
	1ns
$end
$scope module exercise1_tb $end
$var wire 1 ! f $end
$var reg 1 " x1 $end
$var reg 1 # x2 $end
$var reg 1 $ x3 $end
$var reg 1 % x4 $end
$scope module ex1 $end
$var wire 1 ! f $end
$var wire 1 " x1 $end
$var wire 1 # x2 $end
$var wire 1 $ x3 $end
$var wire 1 % x4 $end
$upscope $end
$upscope $end
$enddefinitions $end
#0
$dumpvars
0%
0$
0#
0"
0!
$end
#20
1%
#40
0%
1$
#60
1%
#80
0%
0$
1#
#100
1%
#120
0%
1$
#140
1!
1%
#160
0!
0%
0$
0#
1"
#180
1%
#200
0%
1$
#220
1!
1%
#240
0!
0%
0$
1#
#260
1!
1%
#280
0%
1$
#300
1%
