dsdLab/Lab9-ApplicationsOfDecoders/Q1-ImplementF/implementF.v
module implementF(a,b,c,d,f);
    input a,b,c,d;
    output f;

    wire [3:0] w;
    assign w = {a,b,c,d};

    wire [0:15] y;

    fourTo16Decoder stage0(w,1'b1,y);

    or(f,y[1],y[3],y[6],y[7],y[9],y[14],y[15]);

endmodule

module fourTo16Decoder(w,En,y);
    input [3:0] w;
    input En;
    output reg [0:15] y;

    integer k;

    always @(w or En)
        for(k = 0; k <= 15; k=k+1)
        if ((w == k) && (En == 1))
            y[k] = 1;
        else 
            y[k] = 0;

endmodule

dsdLab/Lab9-ApplicationsOfDecoders/Q1-ImplementF/implementF_tb.v
`timescale 1ns/1ns
`include "implementF.v"

module implementF_tb();
reg a,b,c,d;
wire f;

implementF q(a,b,c,d,f);
initial 
begin 
    $dumpfile("implementF_tb.vcd");
    $dumpvars(0,implementF_tb);

	a=0; b=0; c=0; d=0;#20;
	a=0; b=0; c=0; d=1;#20;
	a=0; b=0; c=1; d=0;#20;
	a=0; b=0; c=1; d=1;#20;
	a=0; b=1; c=0; d=0;#20;
	a=0; b=1; c=0; d=1;#20;
	a=0; b=1; c=1; d=0;#20;
	a=0; b=1; c=1; d=1;#20;
	a=1; b=0; c=0; d=0;#20;
	a=1; b=0; c=0; d=1;#20;
	a=1; b=0; c=1; d=0;#20;
	a=1; b=0; c=1; d=1;#20;
	a=1; b=1; c=0; d=0;#20;
	a=1; b=1; c=0; d=1;#20;
	a=1; b=1; c=1; d=0;#20;
	a=1; b=1; c=1; d=1;#20;
    
	$display("Test Complete");

end
endmodule

dsdLab/Lab9-ApplicationsOfDecoders/Q1-ImplementF/implementF_tb.vcd
$date
	Mon Oct 31 14:20:02 2022
$end
$version
	Icarus Verilog
$end
$timescale
	1ns
$end
$scope module implementF_tb $end
$var wire 1 ! f $end
$var reg 1 " a $end
$var reg 1 # b $end
$var reg 1 $ c $end
$var reg 1 % d $end
$scope module q $end
$var wire 1 " a $end
$var wire 1 # b $end
$var wire 1 $ c $end
$var wire 1 % d $end
$var wire 1 ! f $end
$var wire 16 & y [0:15] $end
$var wire 4 ' w [3:0] $end
$scope module stage0 $end
$var wire 1 ( En $end
$var wire 4 ) w [3:0] $end
$var reg 16 * y [0:15] $end
$var integer 32 + k [31:0] $end
$upscope $end
$upscope $end
$upscope $end
$enddefinitions $end
#0
$dumpvars
b10000 +
b1000000000000000 *
b0 )
1(
b0 '
b1000000000000000 &
0%
0$
0#
0"
0!
$end
#20
1!
b100000000000000 &
b100000000000000 *
b10000 +
b1 '
b1 )
1%
#40
0!
b10000000000000 &
b10000000000000 *
b10000 +
0%
b10 '
b10 )
1$
#60
1!
b1000000000000 &
b1000000000000 *
b10000 +
b11 '
b11 )
1%
#80
0!
b100000000000 &
b100000000000 *
b10000 +
0%
0$
b100 '
b100 )
1#
#100
b10000000000 &
b10000000000 *
b10000 +
b101 '
b101 )
1%
#120
1!
b1000000000 &
b1000000000 *
b10000 +
0%
b110 '
b110 )
1$
#140
b100000000 &
b100000000 *
b10000 +
b111 '
b111 )
1%
#160
0!
b10000000 &
b10000000 *
b10000 +
0%
0$
0#
b1000 '
b1000 )
1"
#180
1!
b1000000 &
b1000000 *
b10000 +
b1001 '
b1001 )
1%
#200
0!
b100000 &
b100000 *
b10000 +
0%
b1010 '
b1010 )
1$
#220
b10000 &
b10000 *
b10000 +
b1011 '
b1011 )
1%
#240
b1000 &
b1000 *
b10000 +
0%
0$
b1100 '
b1100 )
1#
#260
b100 &
b100 *
b10000 +
b1101 '
b1101 )
1%
#280
1!
b10 &
b10 *
b10000 +
0%
b1110 '
b1110 )
1$
#300
b1 &
b1 *
b10000 +
b1111 '
b1111 )
1%
