dsdLab/Lab10-FlipFlopsAndRegisters/Q1D-FF-AsyncReset/dFF.v
module dFF(d,clk,reset,q);
    input d,clk,reset;
    output reg q;

    always @(posedge clk)
        if (!reset)
            q <= d;

    always @(reset)
        if (reset)
            q <= 0;

endmodule

dsdLab/Lab10-FlipFlopsAndRegisters/Q1D-FF-AsyncReset/dFF_tb.v
`timescale 1ns/1ns
`include "dFF.v"

module dFF_tb();
reg d,clk,reset;
wire q;

dFF dFFq(d,clk,reset,q);
always #20 clk = ~clk;
initial
begin
    $dumpfile("dFF_tb.vcd");
    $dumpvars(0,dFF_tb);
    clk = 0;
    #80 $finish;
end
initial
begin
    d=1; reset=1;#10;
    d=1; reset=0;#20;
    d=1; reset=1;#10;
    d=0; reset=1;#10;
    d=1; reset=0;#20;
    d=0; reset=0;#10;
    $display("Test complete");
end
endmodule

dsdLab/Lab10-FlipFlopsAndRegisters/Q1D-FF-AsyncReset/dFF_tb.vcd
$date
	Mon Nov  7 16:07:56 2022
$end
$version
	Icarus Verilog
$end
$timescale
	1ns
$end
$scope module dFF_tb $end
$var wire 1 ! q $end
$var reg 1 " clk $end
$var reg 1 # d $end
$var reg 1 $ reset $end
$scope module dFFq $end
$var wire 1 " clk $end
$var wire 1 # d $end
$var wire 1 $ reset $end
$var reg 1 ! q $end
$upscope $end
$upscope $end
$enddefinitions $end
#0
$dumpvars
1$
1#
0"
0!
$end
#10
0$
#20
1!
1"
#30
0!
1$
#40
0#
0"
#50
0$
1#
#60
1!
1"
#70
0#
